{
  "version": 1,
  "sessionId": "8ae44d96-2c44-4e76-89f0-13b16562fcd3",
  "status": "running",
  "startedAt": "2026-03-13T10:41:17.906Z",
  "updatedAt": "2026-03-13T11:08:49.868Z",
  "currentIteration": 2,
  "maxIterations": 0,
  "tasksCompleted": 2,
  "isPaused": false,
  "agentPlugin": "codex",
  "trackerState": {
    "plugin": "json",
    "prdPath": "./tasks/prd.json",
    "totalTasks": 6,
    "tasks": [
      {
        "id": "US-001",
        "title": "Define CLI contract and output layout",
        "status": "completed",
        "completedInSession": true
      },
      {
        "id": "US-002",
        "title": "Emit Typst from digital PDFs",
        "status": "completed",
        "completedInSession": true
      },
      {
        "id": "US-003",
        "title": "Add OCR support for scanned Korean and English PDFs",
        "status": "open",
        "completedInSession": false
      },
      {
        "id": "US-004",
        "title": "Convert tables, images, and captions",
        "status": "open",
        "completedInSession": false
      },
      {
        "id": "US-005",
        "title": "Support strict and non-strict conversion modes",
        "status": "open",
        "completedInSession": false
      },
      {
        "id": "US-006",
        "title": "Validate compileability and regression coverage",
        "status": "open",
        "completedInSession": false
      }
    ]
  },
  "iterations": [
    {
      "iteration": 1,
      "status": "completed",
      "taskId": "US-001",
      "taskTitle": "Define CLI contract and output layout",
      "taskCompleted": true,
      "durationMs": 258410,
      "startedAt": "2026-03-13T10:41:26.273Z",
      "endedAt": "2026-03-13T10:45:44.683Z"
    },
    {
      "iteration": 2,
      "status": "completed",
      "taskId": "US-002",
      "taskTitle": "Emit Typst from digital PDFs",
      "taskCompleted": true,
      "durationMs": 780918,
      "startedAt": "2026-03-13T10:45:47.479Z",
      "endedAt": "2026-03-13T10:58:48.397Z"
    }
  ],
  "skippedTaskIds": [],
  "cwd": "/Volumes/990EVO+/workspace/pdf-to-typst",
  "activeTaskIds": [],
  "subagentPanelVisible": false
}